[
  {
    "title": "Lesson 1:\nNumbers 1-10",
    "description": "Basic counting is essential. Practice these numbers: uno, dos, tres, cuatro, cinco, seis, siete, ocho, nueve, diez.",
    "dialogue": [
      {
        "speaker": "A",
        "gender": "female",
        "spanish": "¿Cuántos años tienes?",
        "english": "How old are you?"
      },
      {
        "speaker": "B",
        "gender": "male",
        "spanish": "Tengo cinco años.",
        "english": "I am five years old."
      },
      {
        "speaker": "A",
        "gender": "female",
        "spanish": "Yo tengo ocho años.",
        "english": "I am eight years old."
      },
      {
        "speaker": "B",
        "gender": "male",
        "spanish": "Mi hermano tiene diez años.",
        "english": "My brother is ten years old."
      }
    ],
    "vocabulary": [
      {
        "spanish": "uno",
        "english": "one"
      },
      {
        "spanish": "dos",
        "english": "two"
      },
      {
        "spanish": "tres",
        "english": "three"
      },
      {
        "spanish": "cuatro",
        "english": "four"
      },
      {
        "spanish": "cinco",
        "english": "five"
      },
      {
        "spanish": "seis",
        "english": "six"
      },
      {
        "spanish": "siete",
        "english": "seven"
      },
      {
        "spanish": "ocho",
        "english": "eight"
      },
      {
        "spanish": "nueve",
        "english": "nine"
      },
      {
        "spanish": "diez",
        "english": "ten"
      }
    ]
  },
  {
    "title": "Lesson 2:\nWhat time is it?",
    "description": "'¿Qué hora es?' = What time is it? 'Es la una' (1 o'clock), 'Son las dos' (2 o'clock). Use 'la' for one, 'las' for other hours.",
    "dialogue": [
      {
        "speaker": "A",
        "gender": "female",
        "spanish": "¿Qué hora es?",
        "english": "What time is it?"
      },
      {
        "speaker": "B",
        "gender": "male",
        "spanish": "Son las tres.",
        "english": "It's three o'clock."
      },
      {
        "speaker": "A",
        "gender": "female",
        "spanish": "¿A qué hora estudias?",
        "english": "What time do you study?"
      },
      {
        "speaker": "B",
        "gender": "male",
        "spanish": "Estudio a las cuatro.",
        "english": "I study at four o'clock."
      }
    ],
    "vocabulary": [
      {
        "spanish": "¿qué hora es?",
        "english": "what time is it?"
      },
      {
        "spanish": "son las...",
        "english": "it's ... o'clock"
      },
      {
        "spanish": "la una",
        "english": "one o'clock"
      },
      {
        "spanish": "estudio",
        "english": "I study"
      }
    ]
  },
  {
    "title": "Lesson 3:\nDays of the Week",
    "description": "Days: lunes, martes, miércoles, jueves, viernes, sábado, domingo. '¿Qué día es hoy?' = What day is today? 'Hoy es...' = Today is...",
    "dialogue": [
      {
        "speaker": "A",
        "gender": "female",
        "spanish": "¿Qué día es hoy?",
        "english": "What day is today?"
      },
      {
        "speaker": "B",
        "gender": "male",
        "spanish": "Hoy es lunes.",
        "english": "Today is Monday."
      },
      {
        "speaker": "A",
        "gender": "female",
        "spanish": "Mañana es martes.",
        "english": "Tomorrow is Tuesday."
      },
      {
        "speaker": "B",
        "gender": "male",
        "spanish": "Sí, el martes estudio español.",
        "english": "Yes, on Tuesday I study Spanish."
      }
    ],
    "vocabulary": [
      {
        "spanish": "lunes",
        "english": "Monday"
      },
      {
        "spanish": "martes",
        "english": "Tuesday"
      },
      {
        "spanish": "miércoles",
        "english": "Wednesday"
      },
      {
        "spanish": "jueves",
        "english": "Thursday"
      },
      {
        "spanish": "viernes",
        "english": "Friday"
      },
      {
        "spanish": "sábado",
        "english": "Saturday"
      },
      {
        "spanish": "domingo",
        "english": "Sunday"
      },
      {
        "spanish": "hoy",
        "english": "today"
      },
      {
        "spanish": "mañana",
        "english": "tomorrow"
      }
    ]
  },
  {
    "title": "Lesson 4:\nNumbers 11-20",
    "description": "Numbers 11-20: once, doce, trece, catorce, quince, dieciséis, diecisiete, dieciocho, diecinueve, veinte.",
    "dialogue": [
      {
        "speaker": "A",
        "gender": "female",
        "spanish": "¿Cuántos años tiene tu hermana?",
        "english": "How old is your sister?"
      },
      {
        "speaker": "B",
        "gender": "male",
        "spanish": "Tiene quince años.",
        "english": "She is fifteen years old."
      },
      {
        "speaker": "A",
        "gender": "female",
        "spanish": "Mi hermano tiene dieciocho.",
        "english": "My brother is eighteen."
      },
      {
        "speaker": "B",
        "gender": "male",
        "spanish": "¿Cuántos estudiantes hay?",
        "english": "How many students are there?"
      },
      {
        "speaker": "A",
        "gender": "female",
        "spanish": "Hay veinte estudiantes.",
        "english": "There are twenty students."
      }
    ],
    "vocabulary": [
      {
        "spanish": "once",
        "english": "eleven"
      },
      {
        "spanish": "doce",
        "english": "twelve"
      },
      {
        "spanish": "trece",
        "english": "thirteen"
      },
      {
        "spanish": "catorce",
        "english": "fourteen"
      },
      {
        "spanish": "quince",
        "english": "fifteen"
      },
      {
        "spanish": "dieciséis",
        "english": "sixteen"
      },
      {
        "spanish": "diecisiete",
        "english": "seventeen"
      },
      {
        "spanish": "dieciocho",
        "english": "eighteen"
      },
      {
        "spanish": "diecinueve",
        "english": "nineteen"
      },
      {
        "spanish": "veinte",
        "english": "twenty"
      }
    ]
  },
  {
    "title": "Lesson 5:\nMonths",
    "description": "Months: enero, febrero, marzo, abril, mayo, junio, julio, agosto, septiembre, octubre, noviembre, diciembre. Not capitalized in Spanish!",
    "dialogue": [
      {
        "speaker": "A",
        "gender": "female",
        "spanish": "¿Cuándo es tu cumpleaños?",
        "english": "When is your birthday?"
      },
      {
        "speaker": "B",
        "gender": "male",
        "spanish": "Mi cumpleaños es en mayo.",
        "english": "My birthday is in May."
      },
      {
        "speaker": "A",
        "gender": "female",
        "spanish": "¿En qué mes estamos?",
        "english": "What month are we in?"
      },
      {
        "speaker": "B",
        "gender": "male",
        "spanish": "Estamos en marzo.",
        "english": "We are in March."
      }
    ],
    "vocabulary": [
      {
        "spanish": "enero",
        "english": "January"
      },
      {
        "spanish": "febrero",
        "english": "February"
      },
      {
        "spanish": "marzo",
        "english": "March"
      },
      {
        "spanish": "abril",
        "english": "April"
      },
      {
        "spanish": "mayo",
        "english": "May"
      },
      {
        "spanish": "junio",
        "english": "June"
      },
      {
        "spanish": "julio",
        "english": "July"
      },
      {
        "spanish": "agosto",
        "english": "August"
      },
      {
        "spanish": "septiembre",
        "english": "September"
      },
      {
        "spanish": "octubre",
        "english": "October"
      },
      {
        "spanish": "noviembre",
        "english": "November"
      },
      {
        "spanish": "diciembre",
        "english": "December"
      },
      {
        "spanish": "cumpleaños",
        "english": "birthday"
      }
    ]
  },
  {
    "title": "Lesson 6:\nNumbers 20-100",
    "description": "Larger numbers: veinte (20), treinta (30), cuarenta (40), cincuenta (50), sesenta (60), setenta (70), ochenta (80), noventa (90), cien (100).",
    "dialogue": [
      {
        "speaker": "A",
        "gender": "female",
        "spanish": "¿Cuántos años tiene tu padre?",
        "english": "How old is your father?"
      },
      {
        "speaker": "B",
        "gender": "male",
        "spanish": "Tiene cincuenta años.",
        "english": "He is fifty years old."
      },
      {
        "speaker": "A",
        "gender": "female",
        "spanish": "Mi madre tiene cuarenta y cinco.",
        "english": "My mother is forty-five."
      },
      {
        "speaker": "B",
        "gender": "male",
        "spanish": "¿Cuánto cuesta?",
        "english": "How much does it cost?"
      },
      {
        "speaker": "A",
        "gender": "female",
        "spanish": "Cuesta treinta euros.",
        "english": "It costs thirty euros."
      }
    ],
    "vocabulary": [
      {
        "spanish": "treinta",
        "english": "thirty"
      },
      {
        "spanish": "cuarenta",
        "english": "forty"
      },
      {
        "spanish": "cincuenta",
        "english": "fifty"
      },
      {
        "spanish": "sesenta",
        "english": "sixty"
      },
      {
        "spanish": "setenta",
        "english": "seventy"
      },
      {
        "spanish": "ochenta",
        "english": "eighty"
      },
      {
        "spanish": "noventa",
        "english": "ninety"
      },
      {
        "spanish": "cien",
        "english": "one hundred"
      },
      {
        "spanish": "cuesta",
        "english": "it costs"
      },
      {
        "spanish": "euros",
        "english": "euros"
      }
    ]
  },
  {
    "title": "Lesson 7:\nTime with minutes",
    "description": "'Y media' = half past. 'Y cuarto' = quarter past. 'Menos cuarto' = quarter to. 'En punto' = exactly/o'clock. 'Por la tarde' = in the afternoon.",
    "dialogue": [
      {
        "speaker": "A",
        "gender": "female",
        "spanish": "¿Qué hora es exactamente?",
        "english": "What time is it exactly?"
      },
      {
        "speaker": "B",
        "gender": "male",
        "spanish": "Son las tres y media.",
        "english": "It's half past three."
      },
      {
        "speaker": "A",
        "gender": "female",
        "spanish": "¿A qué hora empieza la clase?",
        "english": "What time does class start?"
      },
      {
        "speaker": "B",
        "gender": "male",
        "spanish": "A las cuatro y cuarto en punto.",
        "english": "At exactly quarter past four."
      },
      {
        "speaker": "A",
        "gender": "female",
        "spanish": "Son las cinco menos cuarto por la tarde.",
        "english": "It's quarter to five in the afternoon."
      }
    ],
    "vocabulary": [
      {
        "spanish": "y media",
        "english": "half past"
      },
      {
        "spanish": "y cuarto",
        "english": "quarter past"
      },
      {
        "spanish": "menos cuarto",
        "english": "quarter to"
      },
      {
        "spanish": "en punto",
        "english": "exactly / on the dot"
      },
      {
        "spanish": "por la tarde",
        "english": "in the afternoon"
      },
      {
        "spanish": "por la noche",
        "english": "in the evening / at night"
      }
    ]
  },
  {
    "title": "Lesson 8:\nDates",
    "description": "'¿Cuál es la fecha?' = What is the date? 'Hoy es el quince de marzo' = Today is the 15th of March. In Spanish, dates use cardinal numbers except for the 1st ('primero').",
    "dialogue": [
      {
        "speaker": "A",
        "gender": "female",
        "spanish": "¿Cuál es la fecha de hoy?",
        "english": "What is today's date?"
      },
      {
        "speaker": "B",
        "gender": "male",
        "spanish": "Hoy es el quince de abril.",
        "english": "Today is the 15th of April."
      },
      {
        "speaker": "A",
        "gender": "female",
        "spanish": "¿Y en qué año estamos?",
        "english": "And what year are we in?"
      },
      {
        "speaker": "B",
        "gender": "male",
        "spanish": "Estamos en el año dos mil veinticinco.",
        "english": "We are in the year 2025."
      }
    ],
    "vocabulary": [
      {
        "spanish": "¿cuál es la fecha?",
        "english": "what is the date?"
      },
      {
        "spanish": "el primero",
        "english": "the first (1st)"
      },
      {
        "spanish": "el día",
        "english": "the day"
      },
      {
        "spanish": "el mes",
        "english": "the month"
      },
      {
        "spanish": "el año",
        "english": "the year"
      }
    ]
  }
]